src/launch_project/__init__.py
src/launch_project/__main__.py
tmux_launch_project-1.0.4.dist-info/METADATA
tmux_launch_project-1.0.4.dist-info/WHEEL
tmux_launch_project-1.0.4.dist-info/entry_points.txt
tmux_launch_project-1.0.4.dist-info/licenses/LICENSE
tmux_launch_project-1.0.4.dist-info/RECORD
