Metadata-Version: 2.4
Name: tmux-launch-project
Version: 1.0.4
Summary: Launch tmux (tmuxifier) sessions in the background and name session to project name
Author-email: hamolicious <hamolicious@hamolicious.net>
License-File: LICENSE
Requires-Python: >=3.10
